rpm/__init__.py
rpm-0.4.0.dist-info/licenses/LICENSE
rpm-0.4.0.dist-info/METADATA
rpm-0.4.0.dist-info/WHEEL
rpm-0.4.0.dist-info/top_level.txt
rpm-0.4.0.dist-info/RECORD
