Metadata-Version: 2.4
Name: rpm
Version: 0.4.0
Summary: Shim RPM module for use in virtualenvs.
Home-page: https://github.com/packit/rpm-shim
Author: Red Hat
Author-email: hello@packit.dev
License: MIT
Keywords: rpm,virtualenv
Classifier: Development Status :: 4 - Beta
Classifier: Environment :: Console
Classifier: Intended Audience :: Developers
Classifier: License :: OSI Approved :: MIT License
Classifier: Operating System :: POSIX :: Linux
Classifier: Programming Language :: Python
Classifier: Programming Language :: Python :: 3
Classifier: Programming Language :: Python :: 3 :: Only
Classifier: Programming Language :: Python :: 3.6
Classifier: Programming Language :: Python :: 3.7
Classifier: Programming Language :: Python :: 3.8
Classifier: Programming Language :: Python :: 3.9
Classifier: Programming Language :: Python :: 3.10
Classifier: Programming Language :: Python :: 3.11
Classifier: Topic :: Software Development
Classifier: Topic :: Utilities
Requires-Python: >=3.6
License-File: LICENSE
Provides-Extra: testing
Requires-Dist: tox; extra == "testing"
Dynamic: license-file
